watchfs/__init__.py
watchfs/__main__.py
watchfs/as_sync.py
watchfs/colorful.py
watchfs/exceptions.py
watchfs/filters.py
watchfs/py.typed
watchfs/rusty.py
watchfs-0.2.0.dist-info/WHEEL
watchfs-0.2.0.dist-info/entry_points.txt
watchfs-0.2.0.dist-info/METADATA
watchfs-0.2.0.dist-info/RECORD
