Metadata-Version: 2.3
Name: watchfs
Version: 0.2.0
Summary: Watch and sync files to another directory
Keywords: watch,sync
Author: Nyakku Shigure
Author-email: Nyakku Shigure <sigure.qaq@gmail.com>
License: MIT
Classifier: Operating System :: OS Independent
Classifier: License :: OSI Approved :: MIT License
Classifier: Programming Language :: Python
Classifier: Programming Language :: Python :: 3
Classifier: Programming Language :: Python :: 3.12
Classifier: Programming Language :: Python :: 3.13
Classifier: Programming Language :: Python :: Implementation :: CPython
Requires-Dist: aiofiles>=24.1.0
Requires-Dist: colored>=2.3.1
Requires-Dist: typing-extensions>=4.15.0
Requires-Dist: watchfiles>=1.1.0
Requires-Python: >=3.12
Project-URL: Documentation, https://github.com/ShigureLab/watchfs
Project-URL: Homepage, https://github.com/ShigureLab/watchfs
Project-URL: Issues, https://github.com/ShigureLab/watchfs/issues
Project-URL: Repository, https://github.com/ShigureLab/watchfs
